filecache/__init__.py
filecache-0.81.dist-info/METADATA
filecache-0.81.dist-info/WHEEL
filecache-0.81.dist-info/top_level.txt
filecache-0.81.dist-info/RECORD
